dive/__init__.py
dive/constants.py
dive/deer.py
dive/deerload.py
dive/models.py
dive/plotting.py
dive/samplers.py
dive/saving.py
dive/test_data.py
dive/utils.py
dive_EPR-0.2.1.dist-info/LICENSE
dive_EPR-0.2.1.dist-info/METADATA
dive_EPR-0.2.1.dist-info/WHEEL
dive_EPR-0.2.1.dist-info/top_level.txt
dive_EPR-0.2.1.dist-info/RECORD
