Metadata-Version: 2.1
Name: dive-EPR
Version: 0.2.1
Summary: Python package for Bayesian analysis of dipolar EPR spectroscopy data through Markov chain Monte Carlo sampling with PyMC.
Author: Sarah Sweger, Lukas Zha
Author-email: Julian Cheung <julianc2477@gmail.com>, Stephan Pribitzer <stephapr@uw.edu>, Stefan Stoll <stst@uw.edu>
License: MIT License
Project-URL: Repository, https://github.com/StollLab/dive
Project-URL: Documentation, https://stolllab.github.io/dive
Keywords: EPR,DEER,Bayesian,MCMC
Classifier: Programming Language :: Python :: 3.10
Classifier: License :: OSI Approved :: MIT License
Classifier: Operating System :: OS Independent
Classifier: Intended Audience :: Science/Research
Classifier: Topic :: Scientific/Engineering
Requires-Python: >=3.9
License-File: LICENSE
Requires-Dist: pymc >=5.10.4
Requires-Dist: deerlab >=1.1.2
Requires-Dist: scipy >=1.11.4
Requires-Dist: matplotlib >=3.9.1
Requires-Dist: numpy >=1.15.0
Requires-Dist: pandas >=2.0.3
Requires-Dist: mkl-service >=2.4.1
Requires-Dist: h5netcdf >=1.3.0
Requires-Dist: pytest >=7.4.4
